{
  "marketId": "newyork",
  "archetypeId": "northeast_mega",
  "years": [
    1970,
    1985,
    1995,
    2005,
    2015,
    2026
  ],
  "byYear": {
    "1970": {
      "version": 1,
      "marketId": "newyork",
      "year": 1970,
      "publicRadioStrength": 0.8870666666666667,
      "spanishLanguageStrength": 0.34240000000000004,
      "blackMusicStrength": 0.4347285714285714,
      "urbanContemporaryStrength": 0.7567240000000001,
      "gospelStrength": 0.4531857142857143,
      "ccmStrength": 0.3260571428571428,
      "countryStrength": 0.010857142857142857,
      "aaaAlternativeStrength": 0.631818181818182,
      "spokenWordStrength": 0.8150099020670887,
      "sportsStrength": 0.9922260483799419,
      "chrResistance": 0.5008454362517603,
      "marketFragmentation": 0.8221564966991236,
      "amResilience": 0.5266666666666668,
      "modernMusicSubstitution": 0,
      "rankTier": "mega",
      "archetypeId": "northeast_mega",
      "region": "Northeast"
    },
    "1985": {
      "version": 1,
      "marketId": "newyork",
      "year": 1985,
      "publicRadioStrength": 0.8870666666666667,
      "spanishLanguageStrength": 0.3684,
      "blackMusicStrength": 0.4347285714285714,
      "urbanContemporaryStrength": 0.7567240000000001,
      "gospelStrength": 0.4531857142857143,
      "ccmStrength": 0.3260571428571428,
      "countryStrength": 0.010857142857142857,
      "aaaAlternativeStrength": 0.631818181818182,
      "spokenWordStrength": 0.8150099020670887,
      "sportsStrength": 0.9922260483799419,
      "chrResistance": 0.4977483639752973,
      "marketFragmentation": 0.8235708966991236,
      "amResilience": 0.5266666666666668,
      "modernMusicSubstitution": 0,
      "rankTier": "mega",
      "archetypeId": "northeast_mega",
      "region": "Northeast"
    },
    "1995": {
      "version": 1,
      "marketId": "newyork",
      "year": 1995,
      "publicRadioStrength": 0.8870666666666667,
      "spanishLanguageStrength": 0.3857333333333334,
      "blackMusicStrength": 0.4347285714285714,
      "urbanContemporaryStrength": 0.7567240000000001,
      "gospelStrength": 0.4531857142857143,
      "ccmStrength": 0.3260571428571428,
      "countryStrength": 0.010857142857142857,
      "aaaAlternativeStrength": 0.631818181818182,
      "spokenWordStrength": 0.8150099020670887,
      "sportsStrength": 0.9922260483799419,
      "chrResistance": 0.49568185126476644,
      "marketFragmentation": 0.8245138300324569,
      "amResilience": 0.5266666666666668,
      "modernMusicSubstitution": 0,
      "rankTier": "mega",
      "archetypeId": "northeast_mega",
      "region": "Northeast"
    },
    "2005": {
      "version": 1,
      "marketId": "newyork",
      "year": 2005,
      "publicRadioStrength": 0.8870666666666667,
      "spanishLanguageStrength": 0.39960000000000007,
      "blackMusicStrength": 0.4347285714285714,
      "urbanContemporaryStrength": 0.7567240000000001,
      "gospelStrength": 0.4531857142857143,
      "ccmStrength": 0.3260571428571428,
      "countryStrength": 0.010857142857142857,
      "aaaAlternativeStrength": 0.631818181818182,
      "spokenWordStrength": 0.8150099020670887,
      "sportsStrength": 0.9922260483799419,
      "chrResistance": 0.49402760552923775,
      "marketFragmentation": 0.8252681766991237,
      "amResilience": 0.5266666666666668,
      "modernMusicSubstitution": 0,
      "rankTier": "mega",
      "archetypeId": "northeast_mega",
      "region": "Northeast"
    },
    "2015": {
      "version": 1,
      "marketId": "newyork",
      "year": 2015,
      "publicRadioStrength": 0.8870666666666667,
      "spanishLanguageStrength": 0.41000000000000003,
      "blackMusicStrength": 0.4347285714285714,
      "urbanContemporaryStrength": 0.7567240000000001,
      "gospelStrength": 0.4531857142857143,
      "ccmStrength": 0.3260571428571428,
      "countryStrength": 0.010857142857142857,
      "aaaAlternativeStrength": 0.631818181818182,
      "spokenWordStrength": 0.8150099020670887,
      "sportsStrength": 0.9922260483799419,
      "chrResistance": 0.560381644936244,
      "marketFragmentation": 0.8258339366991236,
      "amResilience": 0.5266666666666668,
      "modernMusicSubstitution": 0.44084568779722244,
      "rankTier": "mega",
      "archetypeId": "northeast_mega",
      "region": "Northeast"
    },
    "2026": {
      "version": 1,
      "marketId": "newyork",
      "year": 2026,
      "publicRadioStrength": 0.8870666666666667,
      "spanishLanguageStrength": 0.4152,
      "blackMusicStrength": 0.4347285714285714,
      "urbanContemporaryStrength": 0.7567240000000001,
      "gospelStrength": 0.4531857142857143,
      "ccmStrength": 0.3260571428571428,
      "countryStrength": 0.010857142857142857,
      "aaaAlternativeStrength": 0.631818181818182,
      "spokenWordStrength": 0.8150099020670887,
      "sportsStrength": 0.9922260483799419,
      "chrResistance": 0.6181880834029588,
      "marketFragmentation": 0.8261168166991236,
      "amResilience": 0.5266666666666668,
      "modernMusicSubstitution": 0.8230152994365763,
      "rankTier": "mega",
      "archetypeId": "northeast_mega",
      "region": "Northeast"
    }
  },
  "latest": {
    "version": 1,
    "marketId": "newyork",
    "year": 2026,
    "publicRadioStrength": 0.8870666666666667,
    "spanishLanguageStrength": 0.4152,
    "blackMusicStrength": 0.4347285714285714,
    "urbanContemporaryStrength": 0.7567240000000001,
    "gospelStrength": 0.4531857142857143,
    "ccmStrength": 0.3260571428571428,
    "countryStrength": 0.010857142857142857,
    "aaaAlternativeStrength": 0.631818181818182,
    "spokenWordStrength": 0.8150099020670887,
    "sportsStrength": 0.9922260483799419,
    "chrResistance": 0.6181880834029588,
    "marketFragmentation": 0.8261168166991236,
    "amResilience": 0.5266666666666668,
    "modernMusicSubstitution": 0.8230152994365763,
    "rankTier": "mega",
    "archetypeId": "northeast_mega",
    "region": "Northeast"
  },
  "derivedAt": "2026-05-17T21:24:26.021Z"
}
